CHANGES.rst
CONTRIBUTING.rst
HEADER.rst
LICENSE
MANIFEST.in
README.rst
pyproject.toml
pytest_rerunfailures.py
setup.cfg
setup.py
test_pytest_rerunfailures.py
tox.ini
pytest_rerunfailures_all_logs.egg-info/PKG-INFO
pytest_rerunfailures_all_logs.egg-info/SOURCES.txt
pytest_rerunfailures_all_logs.egg-info/dependency_links.txt
pytest_rerunfailures_all_logs.egg-info/entry_points.txt
pytest_rerunfailures_all_logs.egg-info/not-zip-safe
pytest_rerunfailures_all_logs.egg-info/requires.txt
pytest_rerunfailures_all_logs.egg-info/top_level.txt